mutt_language_server/__init__.py
mutt_language_server/__main__.py
mutt_language_server/_metainfo.py
mutt_language_server/_shtab.py
mutt_language_server/_version.py
mutt_language_server/finders.py
mutt_language_server/py.typed
mutt_language_server/schema.py
mutt_language_server/server.py
mutt_language_server/utils.py
mutt_language_server/assets/json/neomuttrc.json
mutt_language_server/assets/queries/import.scm
mutt_language_server/misc/__init__.py
mutt_language_server-0.0.17.data/data/share/bash-completion/completions/mutt-language-server
mutt_language_server-0.0.17.data/data/share/man/man1/mutt-language-server.1
mutt_language_server-0.0.17.data/data/share/zsh/site-functions/_mutt-language-server
mutt_language_server-0.0.17.dist-info/licenses/LICENSE
mutt_language_server-0.0.17.dist-info/METADATA
mutt_language_server-0.0.17.dist-info/WHEEL
mutt_language_server-0.0.17.dist-info/entry_points.txt
mutt_language_server-0.0.17.dist-info/top_level.txt
mutt_language_server-0.0.17.dist-info/RECORD
