Metadata-Version: 2.4
Name: mutt-language-server
Version: 0.0.17
Summary: mutt language server
Author-email: "Wu, Zhenyu" <wuzhenyu@ustc.edu>
License: GPL v3
Project-URL: Homepage, https://mutt-language-server.readthedocs.io
Project-URL: Download, https://github.com/neomutt/mutt-language-server/releases
Project-URL: Bug Report, https://github.com/neomutt/mutt-language-server/issues
Project-URL: Source, https://github.com/neomutt/mutt-language-server
Keywords: mutt,language server
Classifier: Development Status :: 3 - Alpha
Classifier: Intended Audience :: Developers
Classifier: Topic :: Software Development :: Build Tools
Classifier: License :: OSI Approved :: GNU General Public License v3 (GPLv3)
Classifier: Operating System :: Microsoft :: Windows
Classifier: Operating System :: POSIX
Classifier: Operating System :: Unix
Classifier: Operating System :: MacOS
Classifier: Programming Language :: Python :: 3 :: Only
Classifier: Programming Language :: Python :: 3
Classifier: Programming Language :: Python :: 3.10
Classifier: Programming Language :: Python :: 3.11
Classifier: Programming Language :: Python :: 3.12
Classifier: Programming Language :: Python :: Implementation :: CPython
Classifier: Programming Language :: Python :: Implementation :: PyPy
Requires-Python: >=3.10
License-File: LICENSE
Requires-Dist: lsp-tree-sitter>=0.1.0
Requires-Dist: pygls>=2.0.0
Requires-Dist: tree-sitter-muttrc>=0.0.4
Provides-Extra: colorize
Requires-Dist: lsp-tree-sitter[colorize]; extra == "colorize"
Provides-Extra: dev
Requires-Dist: pytest-cov; extra == "dev"
Provides-Extra: misc
Requires-Dist: lsp-tree-sitter[misc]; extra == "misc"
Dynamic: license-file
